AUTHORS
CHANGELOG
LICENSE
MANIFEST.in
README.rst
setup.py
jweede/__init__.py
jweede.recipe.template.egg-info/PKG-INFO
jweede.recipe.template.egg-info/SOURCES.txt
jweede.recipe.template.egg-info/dependency_links.txt
jweede.recipe.template.egg-info/entry_points.txt
jweede.recipe.template.egg-info/namespace_packages.txt
jweede.recipe.template.egg-info/requires.txt
jweede.recipe.template.egg-info/top_level.txt
jweede.recipe.template.egg-info/zip-safe
jweede/recipe/__init__.py
jweede/recipe/template/__init__.py