Metadata-Version: 1.1
Name: jweede.recipe.template
Version: 1.2.4
Summary: Buildout recipe for making files out of Jinja2 templates
Home-page: http://github.com/jweede/amplecode.recipe.template
Author: Jon Wedaman
Author-email: jweede@gmail.com
License: BSD
Keywords: zc.buildout recipe template Jinja2
Platform: UNKNOWN
Classifier: Framework :: Buildout
Classifier: Intended Audience :: Developers
Classifier: License :: OSI Approved :: BSD License
Classifier: Programming Language :: Python
Classifier: Topic :: Software Development
Classifier: Topic :: Software Development :: Code Generators
Classifier: Topic :: Software Development :: Pre-processors
